pse/structuring_engine.py
pse/types/array.py
pse/types/boolean.py
pse/types/enum.py
pse/types/integer.py
pse/types/key_value.py
pse/types/number.py
pse/types/object.py
pse/types/string.py
pse/types/whitespace.py
pse/types/base/any.py
pse/types/base/chain.py
pse/types/base/character.py
pse/types/base/encapsulated.py
pse/types/base/loop.py
pse/types/base/phrase.py
pse/types/base/wait_for.py
pse/types/grammar/__init__.py
pse/types/grammar/lark.py
pse/types/grammar/default_grammars/bash.lark
pse/types/grammar/default_grammars/bash.py
pse/types/grammar/default_grammars/python.lark
pse/types/grammar/default_grammars/python.py
pse/types/json/__init__.py
pse/types/json/any_json_schema.py
pse/types/json/json_array.py
pse/types/json/json_key_value.py
pse/types/json/json_number.py
pse/types/json/json_object.py
pse/types/json/json_string.py
pse/types/json/json_value.py
pse/types/json/schema_sources/from_function.py
pse/types/json/schema_sources/from_pydantic.py
pse/types/misc/fenced_freeform.py
pse/types/misc/freeform.py
pse/types/xml/xml_encapsulated.py
pse/types/xml/xml_tag.py
pse/util/generate_mlx.py
pse/util/get_top_logits.py
pse/util/jax_mixin.py
pse/util/tf_mixin.py
pse/util/torch_mixin.py
pse-2025.6.1.dist-info/METADATA
pse-2025.6.1.dist-info/WHEEL
pse-2025.6.1.dist-info/licenses/LICENSE
pse-2025.6.1.dist-info/RECORD
