Metadata-Version: 2.4
Name: pse
Version: 2025.6.1
Summary: Proxy Structuring Engine: Stateful AI-generated output with a focus on creativity, speed, and structure.
Project-URL: homepage, https://github.com/TheProxyCompany/proxy-structuring-engine
Project-URL: documentation, https://github.com/TheProxyCompany/proxy-structuring-engine#readme
Project-URL: source, https://github.com/TheProxyCompany/proxy-structuring-engine
Author-email: Jack Wind <jckwind11@gmail.com>, The Proxy Company <contact@theproxy.company>
License:                                  Apache License
License-File: LICENSE
Requires-Python: >=3.11
Requires-Dist: docstring-parser
Requires-Dist: lark
Requires-Dist: protobuf
Requires-Dist: pse-core
Requires-Dist: pydantic
Requires-Dist: regex
Requires-Dist: tokenizers
Requires-Dist: tqdm
Requires-Dist: transformers
Requires-Dist: typing-extensions
Requires-Dist: wheel
Provides-Extra: dev
Requires-Dist: coverage; extra == 'dev'
Requires-Dist: flake8; extra == 'dev'
Requires-Dist: ipykernel; extra == 'dev'
Requires-Dist: pytest; extra == 'dev'
Requires-Dist: pytest-cov; extra == 'dev'
Requires-Dist: ruff; extra == 'dev'
Requires-Dist: sentencepiece; extra == 'dev'
Provides-Extra: jax
Requires-Dist: accelerate; extra == 'jax'
Requires-Dist: jax; extra == 'jax'
Provides-Extra: mlx
Requires-Dist: mlx; extra == 'mlx'
Requires-Dist: mlx-proxy; extra == 'mlx'
Provides-Extra: tensorflow
Requires-Dist: accelerate; extra == 'tensorflow'
Requires-Dist: tensorflow; extra == 'tensorflow'
Provides-Extra: torch
Requires-Dist: accelerate; extra == 'torch'
Requires-Dist: torch; extra == 'torch'
